ezcfn/__init__.py
ezcfn/__main__.py
ezcfn/resolution/__init__.py
ezcfn/resolution/tasks.py
ezcfn/resolution/helper/__init__.py
ezcfn/resolution/helper/filesystem.py
ezcfn/resolution/helper/logging.py
ezcfn/resolution/helper/process.py
ezcfn/resolution/helper/stdsync.py
ezcfn/resolution/resolver/__init__.py
ezcfn/resolution/resolver/_lambda.py
ezcfn/resolution/resolver/api_gateway.py
ezcfn/resolution/resolver/api_gateway_v2.py
ezcfn/resolution/resolver/cloudformation.py
ezcfn_victorykit-1.0.0a25.dist-info/LICENSE
ezcfn_victorykit-1.0.0a25.dist-info/METADATA
ezcfn_victorykit-1.0.0a25.dist-info/WHEEL
ezcfn_victorykit-1.0.0a25.dist-info/entry_points.txt
ezcfn_victorykit-1.0.0a25.dist-info/top_level.txt
ezcfn_victorykit-1.0.0a25.dist-info/zip-safe
ezcfn_victorykit-1.0.0a25.dist-info/RECORD
