Metadata-Version: 2.1
Name: ezcfn-victorykit
Version: 1.0.0a25
Summary: Bootstrap for AWS CloudFormation templates
Home-page: https://victorykit.bitbucket.io/ezcfn
Author: Tiara Rodney
Author-email: t.rodney@victoryk.it
License: UNKNOWN
Project-URL: Bug Tracker, https://bitbucket.org/victorykit/ezcfn/jira
Platform: UNKNOWN
Requires-Python: >=3.7
License-File: LICENSE
Requires-Dist: cfn-flip
